{
    "kind": "Listing",
    "data": {
        "after": null,
        "dist": 7,
        "modhash": "",
        "geo_filter": "",
        "children": [
            {
                "kind": "t1",
                "data": {
                    "subreddit_id": "t5_2k1084",
                    "approved_at_utc": null,
                    "author_is_blocked": false,
                    "comment_type": null,
                    "link_title": "Sesh doesn\u2019t get much mention around here.",
                    "mod_reason_by": null,
                    "banned_by": null,
                    "ups": 3,
                    "num_reports": null,
                    "author_flair_type": "text",
                    "total_awards_received": 0,
                    "subreddit": "NicotinePouch",
                    "link_author": "Busy_Appointment6932",
                    "likes": null,
                    "replies": "",
                    "user_reports": [],
                    "saved": false,
                    "id": "kroewyp",
                    "banned_at_utc": null,
                    "mod_reason_title": null,
                    "gilded": 0,
                    "archived": true,
                    "collapsed_reason_code": null,
                    "no_follow": true,
                    "author": "MaxCunningham_Sesh",
                    "num_comments": 45,
                    "can_mod_post": false,
                    "send_replies": true,
                    "parent_id": "t1_kroc6oj",
                    "score": 3,
                    "author_fullname": "t2_uqmd72dkg",
                    "over_18": true,
                    "report_reasons": null,
                    "removal_reason": null,
                    "approved_by": null,
                    "controversiality": 0,
                    "body": "My pleasure! It's really helpful getting this feedback and it gives us that extra push hearing you guys talk about it.",
                    "edited": false,
                    "top_awarded_type": null,
                    "downs": 0,
                    "author_flair_css_class": null,
                    "is_submitter": false,
                    "collapsed": false,
                    "author_flair_richtext": [],
                    "author_patreon_flair": false,
                    "body_html": "&lt;div class=\"md\"&gt;&lt;p&gt;My pleasure! It&amp;#39;s really helpful getting this feedback and it gives us that extra push hearing you guys talk about it.&lt;/p&gt;\n&lt;/div&gt;",
                    "gildings": {},
                    "collapsed_reason": null,
                    "distinguished": null,
                    "associated_award": null,
                    "stickied": false,
                    "author_premium": false,
                    "can_gild": false,
                    "link_id": "t3_1anot67",
                    "unrepliable_reason": null,
                    "author_flair_text_color": null,
                    "score_hidden": false,
                    "permalink": "/r/NicotinePouch/comments/1anot67/sesh_doesnt_get_much_mention_around_here/kroewyp/",
                    "subreddit_type": "public",
                    "link_permalink": "https://www.reddit.com/r/NicotinePouch/comments/1anot67/sesh_doesnt_get_much_mention_around_here/",
                    "name": "t1_kroewyp",
                    "author_flair_template_id": null,
                    "subreddit_name_prefixed": "r/NicotinePouch",
                    "author_flair_text": null,
                    "treatment_tags": [],
                    "created": 1708641552.0,
                    "created_utc": 1708641552.0,
                    "awarders": [],
                    "all_awardings": [],
                    "locked": false,
                    "author_flair_background_color": null,
                    "collapsed_because_crowd_control": null,
                    "mod_reports": [],
                    "quarantine": false,
                    "mod_note": null,
                    "link_url": "https://i.redd.it/3zxcetvecthc1.jpeg"
                }
            },
            {
                "kind": "t1",
                "data": {
                    "subreddit_id": "t5_2k1084",
                    "approved_at_utc": null,
                    "author_is_blocked": false,
                    "comment_type": null,
                    "link_title": "Sesh doesn\u2019t get much mention around here.",
                    "mod_reason_by": null,
                    "banned_by": null,
                    "ups": 3,
                    "num_reports": null,
                    "author_flair_type": "text",
                    "total_awards_received": 0,
                    "subreddit": "NicotinePouch",
                    "link_author": "Busy_Appointment6932",
                    "likes": null,
                    "replies": "",
                    "user_reports": [],
                    "saved": false,
                    "id": "krod39d",
                    "banned_at_utc": null,
                    "mod_reason_title": null,
                    "gilded": 0,
                    "archived": true,
                    "collapsed_reason_code": null,
                    "no_follow": true,
                    "author": "MaxCunningham_Sesh",
                    "num_comments": 45,
                    "can_mod_post": false,
                    "send_replies": true,
                    "parent_id": "t1_krobl15",
                    "score": 3,
                    "author_fullname": "t2_uqmd72dkg",
                    "over_18": true,
                    "report_reasons": null,
                    "removal_reason": null,
                    "approved_by": null,
                    "controversiality": 0,
                    "body": "Thanks, great to know that people care about the fact it's made in Sweden. It matters to me, but we've had so many offers to move to facilities in China or India but anytime I've tried samples the quality diff. is so noticeable to me. Obviously, shipping is more expensive, and we're looking at either US/CDN facilities as we grow but for now we're sticking with Sweden.",
                    "edited": false,
                    "top_awarded_type": null,
                    "downs": 0,
                    "author_flair_css_class": null,
                    "is_submitter": false,
                    "collapsed": false,
                    "author_flair_richtext": [],
                    "author_patreon_flair": false,
                    "body_html": "&lt;div class=\"md\"&gt;&lt;p&gt;Thanks, great to know that people care about the fact it&amp;#39;s made in Sweden. It matters to me, but we&amp;#39;ve had so many offers to move to facilities in China or India but anytime I&amp;#39;ve tried samples the quality diff. is so noticeable to me. Obviously, shipping is more expensive, and we&amp;#39;re looking at either US/CDN facilities as we grow but for now we&amp;#39;re sticking with Sweden.&lt;/p&gt;\n&lt;/div&gt;",
                    "gildings": {},
                    "collapsed_reason": null,
                    "distinguished": null,
                    "associated_award": null,
                    "stickied": false,
                    "author_premium": false,
                    "can_gild": false,
                    "link_id": "t3_1anot67",
                    "unrepliable_reason": null,
                    "author_flair_text_color": null,
                    "score_hidden": false,
                    "permalink": "/r/NicotinePouch/comments/1anot67/sesh_doesnt_get_much_mention_around_here/krod39d/",
                    "subreddit_type": "public",
                    "link_permalink": "https://www.reddit.com/r/NicotinePouch/comments/1anot67/sesh_doesnt_get_much_mention_around_here/",
                    "name": "t1_krod39d",
                    "author_flair_template_id": null,
                    "subreddit_name_prefixed": "r/NicotinePouch",
                    "author_flair_text": null,
                    "treatment_tags": [],
                    "created": 1708640920.0,
                    "created_utc": 1708640920.0,
                    "awarders": [],
                    "all_awardings": [],
                    "locked": false,
                    "author_flair_background_color": null,
                    "collapsed_because_crowd_control": null,
                    "mod_reports": [],
                    "quarantine": false,
                    "mod_note": null,
                    "link_url": "https://i.redd.it/3zxcetvecthc1.jpeg"
                }
            },
            {
                "kind": "t1",
                "data": {
                    "subreddit_id": "t5_2k1084",
                    "approved_at_utc": null,
                    "author_is_blocked": false,
                    "comment_type": null,
                    "link_title": "Sesh doesn\u2019t get much mention around here.",
                    "mod_reason_by": null,
                    "banned_by": null,
                    "ups": 2,
                    "num_reports": null,
                    "author_flair_type": "text",
                    "total_awards_received": 0,
                    "subreddit": "NicotinePouch",
                    "link_author": "Busy_Appointment6932",
                    "likes": null,
                    "replies": "",
                    "user_reports": [],
                    "saved": false,
                    "id": "krobyok",
                    "banned_at_utc": null,
                    "mod_reason_title": null,
                    "gilded": 0,
                    "archived": true,
                    "collapsed_reason_code": null,
                    "no_follow": true,
                    "author": "MaxCunningham_Sesh",
                    "num_comments": 45,
                    "can_mod_post": false,
                    "send_replies": true,
                    "parent_id": "t1_krob586",
                    "score": 2,
                    "author_fullname": "t2_uqmd72dkg",
                    "over_18": true,
                    "report_reasons": null,
                    "removal_reason": null,
                    "approved_by": null,
                    "controversiality": 0,
                    "body": "haha that's awesome, and it means a lot. Still relatively new to Reddit but someone sent me the thread so I wanted to jump in.",
                    "edited": false,
                    "top_awarded_type": null,
                    "downs": 0,
                    "author_flair_css_class": null,
                    "is_submitter": false,
                    "collapsed": false,
                    "author_flair_richtext": [],
                    "author_patreon_flair": false,
                    "body_html": "&lt;div class=\"md\"&gt;&lt;p&gt;haha that&amp;#39;s awesome, and it means a lot. Still relatively new to Reddit but someone sent me the thread so I wanted to jump in.&lt;/p&gt;\n&lt;/div&gt;",
                    "gildings": {},
                    "collapsed_reason": null,
                    "distinguished": null,
                    "associated_award": null,
                    "stickied": false,
                    "author_premium": false,
                    "can_gild": false,
                    "link_id": "t3_1anot67",
                    "unrepliable_reason": null,
                    "author_flair_text_color": null,
                    "score_hidden": false,
                    "permalink": "/r/NicotinePouch/comments/1anot67/sesh_doesnt_get_much_mention_around_here/krobyok/",
                    "subreddit_type": "public",
                    "link_permalink": "https://www.reddit.com/r/NicotinePouch/comments/1anot67/sesh_doesnt_get_much_mention_around_here/",
                    "name": "t1_krobyok",
                    "author_flair_template_id": null,
                    "subreddit_name_prefixed": "r/NicotinePouch",
                    "author_flair_text": null,
                    "treatment_tags": [],
                    "created": 1708640535.0,
                    "created_utc": 1708640535.0,
                    "awarders": [],
                    "all_awardings": [],
                    "locked": false,
                    "author_flair_background_color": null,
                    "collapsed_because_crowd_control": null,
                    "mod_reports": [],
                    "quarantine": false,
                    "mod_note": null,
                    "link_url": "https://i.redd.it/3zxcetvecthc1.jpeg"
                }
            },
            {
                "kind": "t1",
                "data": {
                    "subreddit_id": "t5_2k1084",
                    "approved_at_utc": null,
                    "author_is_blocked": false,
                    "comment_type": null,
                    "link_title": "Sesh doesn\u2019t get much mention around here.",
                    "mod_reason_by": null,
                    "banned_by": null,
                    "ups": 3,
                    "num_reports": null,
                    "author_flair_type": "text",
                    "total_awards_received": 0,
                    "subreddit": "NicotinePouch",
                    "link_author": "Busy_Appointment6932",
                    "likes": null,
                    "replies": "",
                    "user_reports": [],
                    "saved": false,
                    "id": "krn4kw4",
                    "banned_at_utc": null,
                    "mod_reason_title": null,
                    "gilded": 0,
                    "archived": true,
                    "collapsed_reason_code": null,
                    "no_follow": true,
                    "author": "MaxCunningham_Sesh",
                    "num_comments": 45,
                    "can_mod_post": false,
                    "send_replies": true,
                    "parent_id": "t1_kpvvc93",
                    "score": 3,
                    "author_fullname": "t2_uqmd72dkg",
                    "over_18": true,
                    "report_reasons": null,
                    "removal_reason": null,
                    "approved_by": null,
                    "controversiality": 0,
                    "body": "Thanks! We're trying, launching with Buc-ee's this month as our first major US chain.",
                    "edited": false,
                    "top_awarded_type": null,
                    "downs": 0,
                    "author_flair_css_class": null,
                    "is_submitter": false,
                    "collapsed": false,
                    "author_flair_richtext": [],
                    "author_patreon_flair": false,
                    "body_html": "&lt;div class=\"md\"&gt;&lt;p&gt;Thanks! We&amp;#39;re trying, launching with Buc-ee&amp;#39;s this month as our first major US chain.&lt;/p&gt;\n&lt;/div&gt;",
                    "gildings": {},
                    "collapsed_reason": null,
                    "distinguished": null,
                    "associated_award": null,
                    "stickied": false,
                    "author_premium": false,
                    "can_gild": false,
                    "link_id": "t3_1anot67",
                    "unrepliable_reason": null,
                    "author_flair_text_color": null,
                    "score_hidden": false,
                    "permalink": "/r/NicotinePouch/comments/1anot67/sesh_doesnt_get_much_mention_around_here/krn4kw4/",
                    "subreddit_type": "public",
                    "link_permalink": "https://www.reddit.com/r/NicotinePouch/comments/1anot67/sesh_doesnt_get_much_mention_around_here/",
                    "name": "t1_krn4kw4",
                    "author_flair_template_id": null,
                    "subreddit_name_prefixed": "r/NicotinePouch",
                    "author_flair_text": null,
                    "treatment_tags": [],
                    "created": 1708626510.0,
                    "created_utc": 1708626510.0,
                    "awarders": [],
                    "all_awardings": [],
                    "locked": false,
                    "author_flair_background_color": null,
                    "collapsed_because_crowd_control": null,
                    "mod_reports": [],
                    "quarantine": false,
                    "mod_note": null,
                    "link_url": "https://i.redd.it/3zxcetvecthc1.jpeg"
                }
            },
            {
                "kind": "t1",
                "data": {
                    "subreddit_id": "t5_2k1084",
                    "approved_at_utc": null,
                    "author_is_blocked": false,
                    "comment_type": null,
                    "link_title": "Sesh doesn\u2019t get much mention around here.",
                    "mod_reason_by": null,
                    "banned_by": null,
                    "ups": 3,
                    "num_reports": null,
                    "author_flair_type": "text",
                    "total_awards_received": 0,
                    "subreddit": "NicotinePouch",
                    "link_author": "Busy_Appointment6932",
                    "likes": null,
                    "replies": "",
                    "user_reports": [],
                    "saved": false,
                    "id": "krmtgm3",
                    "banned_at_utc": null,
                    "mod_reason_title": null,
                    "gilded": 0,
                    "archived": true,
                    "collapsed_reason_code": null,
                    "no_follow": true,
                    "author": "MaxCunningham_Sesh",
                    "num_comments": 45,
                    "can_mod_post": false,
                    "send_replies": true,
                    "parent_id": "t1_kq2j7bl",
                    "score": 3,
                    "author_fullname": "t2_uqmd72dkg",
                    "over_18": true,
                    "report_reasons": null,
                    "removal_reason": null,
                    "approved_by": null,
                    "controversiality": 0,
                    "body": "Yes we are Canadian based (Vancouver) that's where I'm from, we only sell our nicotine gum in Canada right now as we're still waiting for our pouch approval from Health Canada. We have a US subsidiary and 2 DCs that we sell our nicotine pouches from in the US. Our pouches are made in our partner's Swedish facility (Helsingborg).",
                    "edited": false,
                    "top_awarded_type": null,
                    "downs": 0,
                    "author_flair_css_class": null,
                    "is_submitter": false,
                    "collapsed": false,
                    "author_flair_richtext": [],
                    "author_patreon_flair": false,
                    "body_html": "&lt;div class=\"md\"&gt;&lt;p&gt;Yes we are Canadian based (Vancouver) that&amp;#39;s where I&amp;#39;m from, we only sell our nicotine gum in Canada right now as we&amp;#39;re still waiting for our pouch approval from Health Canada. We have a US subsidiary and 2 DCs that we sell our nicotine pouches from in the US. Our pouches are made in our partner&amp;#39;s Swedish facility (Helsingborg).&lt;/p&gt;\n&lt;/div&gt;",
                    "gildings": {},
                    "collapsed_reason": null,
                    "distinguished": null,
                    "associated_award": null,
                    "stickied": false,
                    "author_premium": false,
                    "can_gild": false,
                    "link_id": "t3_1anot67",
                    "unrepliable_reason": null,
                    "author_flair_text_color": null,
                    "score_hidden": false,
                    "permalink": "/r/NicotinePouch/comments/1anot67/sesh_doesnt_get_much_mention_around_here/krmtgm3/",
                    "subreddit_type": "public",
                    "link_permalink": "https://www.reddit.com/r/NicotinePouch/comments/1anot67/sesh_doesnt_get_much_mention_around_here/",
                    "name": "t1_krmtgm3",
                    "author_flair_template_id": null,
                    "subreddit_name_prefixed": "r/NicotinePouch",
                    "author_flair_text": null,
                    "treatment_tags": [],
                    "created": 1708622630.0,
                    "created_utc": 1708622630.0,
                    "awarders": [],
                    "all_awardings": [],
                    "locked": false,
                    "author_flair_background_color": null,
                    "collapsed_because_crowd_control": null,
                    "mod_reports": [],
                    "quarantine": false,
                    "mod_note": null,
                    "link_url": "https://i.redd.it/3zxcetvecthc1.jpeg"
                }
            },
            {
                "kind": "t1",
                "data": {
                    "subreddit_id": "t5_2k1084",
                    "approved_at_utc": null,
                    "author_is_blocked": false,
                    "comment_type": null,
                    "link_title": "Sesh doesn\u2019t get much mention around here.",
                    "mod_reason_by": null,
                    "banned_by": null,
                    "ups": 4,
                    "num_reports": null,
                    "author_flair_type": "text",
                    "total_awards_received": 0,
                    "subreddit": "NicotinePouch",
                    "link_author": "Busy_Appointment6932",
                    "likes": null,
                    "replies": "",
                    "user_reports": [],
                    "saved": false,
                    "id": "krmmuyq",
                    "banned_at_utc": null,
                    "mod_reason_title": null,
                    "gilded": 0,
                    "archived": true,
                    "collapsed_reason_code": null,
                    "no_follow": false,
                    "author": "MaxCunningham_Sesh",
                    "num_comments": 45,
                    "can_mod_post": false,
                    "send_replies": true,
                    "parent_id": "t1_kpxn4vr",
                    "score": 4,
                    "author_fullname": "t2_uqmd72dkg",
                    "over_18": true,
                    "report_reasons": null,
                    "removal_reason": null,
                    "approved_by": null,
                    "controversiality": 0,
                    "body": "It's not rebranded, it's a proprietary formula and we actually have a granted patent on the gumbase we use in our pouches which gives it a softness and chewiness and helps deliver the nicotine more efficiently. We partnered with the 'godfather' of nicotine pouches, Thomas Ericsson, on our formula.  Thomas is the original inventor of Zyn, Dryft, Nordic Spirit pouches along with assisting on many other formulas you see in Europe and the US today. I always loved the Swedish pouches, but I could never find them in the US and so we wanted to bring that spirit to the US &amp; Canadian markets. We only have regulatory filings in US on it but Europe is definitely something we might explore in the future.",
                    "edited": false,
                    "top_awarded_type": null,
                    "downs": 0,
                    "author_flair_css_class": null,
                    "is_submitter": false,
                    "collapsed": false,
                    "author_flair_richtext": [],
                    "author_patreon_flair": false,
                    "body_html": "&lt;div class=\"md\"&gt;&lt;p&gt;It&amp;#39;s not rebranded, it&amp;#39;s a proprietary formula and we actually have a granted patent on the gumbase we use in our pouches which gives it a softness and chewiness and helps deliver the nicotine more efficiently. We partnered with the &amp;#39;godfather&amp;#39; of nicotine pouches, Thomas Ericsson, on our formula.  Thomas is the original inventor of Zyn, Dryft, Nordic Spirit pouches along with assisting on many other formulas you see in Europe and the US today. I always loved the Swedish pouches, but I could never find them in the US and so we wanted to bring that spirit to the US &amp;amp; Canadian markets. We only have regulatory filings in US on it but Europe is definitely something we might explore in the future.&lt;/p&gt;\n&lt;/div&gt;",
                    "gildings": {},
                    "collapsed_reason": null,
                    "distinguished": null,
                    "associated_award": null,
                    "stickied": false,
                    "author_premium": false,
                    "can_gild": false,
                    "link_id": "t3_1anot67",
                    "unrepliable_reason": null,
                    "author_flair_text_color": null,
                    "score_hidden": false,
                    "permalink": "/r/NicotinePouch/comments/1anot67/sesh_doesnt_get_much_mention_around_here/krmmuyq/",
                    "subreddit_type": "public",
                    "link_permalink": "https://www.reddit.com/r/NicotinePouch/comments/1anot67/sesh_doesnt_get_much_mention_around_here/",
                    "name": "t1_krmmuyq",
                    "author_flair_template_id": null,
                    "subreddit_name_prefixed": "r/NicotinePouch",
                    "author_flair_text": null,
                    "treatment_tags": [],
                    "created": 1708620098.0,
                    "created_utc": 1708620098.0,
                    "awarders": [],
                    "all_awardings": [],
                    "locked": false,
                    "author_flair_background_color": null,
                    "collapsed_because_crowd_control": null,
                    "mod_reports": [],
                    "quarantine": false,
                    "mod_note": null,
                    "link_url": "https://i.redd.it/3zxcetvecthc1.jpeg"
                }
            },
            {
                "kind": "t1",
                "data": {
                    "subreddit_id": "t5_2k1084",
                    "approved_at_utc": null,
                    "author_is_blocked": false,
                    "comment_type": null,
                    "link_title": "Sesh doesn\u2019t get much mention around here.",
                    "mod_reason_by": null,
                    "banned_by": null,
                    "ups": 4,
                    "num_reports": null,
                    "author_flair_type": "text",
                    "total_awards_received": 0,
                    "subreddit": "NicotinePouch",
                    "link_author": "Busy_Appointment6932",
                    "likes": null,
                    "replies": "",
                    "user_reports": [],
                    "saved": false,
                    "id": "krmlz7r",
                    "banned_at_utc": null,
                    "mod_reason_title": null,
                    "gilded": 0,
                    "archived": true,
                    "collapsed_reason_code": null,
                    "no_follow": false,
                    "author": "MaxCunningham_Sesh",
                    "num_comments": 45,
                    "can_mod_post": false,
                    "send_replies": true,
                    "parent_id": "t3_1anot67",
                    "score": 4,
                    "author_fullname": "t2_uqmd72dkg",
                    "over_18": true,
                    "report_reasons": null,
                    "removal_reason": null,
                    "approved_by": null,
                    "controversiality": 0,
                    "body": "Really appreciate this everyone. We work so hard on our products, and I'm really happy more people are starting to notice. I was originally a snus user, then vaper, I always had this dry cough and chest pain, then someone introduced me to a nic pouch in Canada (whitefox) which I loved. The only drawback was that it would start to tear up my gums and the menthol was so intense. That's where this all started 5 years ago, we've come a long way...",
                    "edited": false,
                    "top_awarded_type": null,
                    "downs": 0,
                    "author_flair_css_class": null,
                    "is_submitter": false,
                    "collapsed": false,
                    "author_flair_richtext": [],
                    "author_patreon_flair": false,
                    "body_html": "&lt;div class=\"md\"&gt;&lt;p&gt;Really appreciate this everyone. We work so hard on our products, and I&amp;#39;m really happy more people are starting to notice. I was originally a snus user, then vaper, I always had this dry cough and chest pain, then someone introduced me to a nic pouch in Canada (whitefox) which I loved. The only drawback was that it would start to tear up my gums and the menthol was so intense. That&amp;#39;s where this all started 5 years ago, we&amp;#39;ve come a long way...&lt;/p&gt;\n&lt;/div&gt;",
                    "gildings": {},
                    "collapsed_reason": null,
                    "distinguished": null,
                    "associated_award": null,
                    "stickied": false,
                    "author_premium": false,
                    "can_gild": false,
                    "link_id": "t3_1anot67",
                    "unrepliable_reason": null,
                    "author_flair_text_color": null,
                    "score_hidden": false,
                    "permalink": "/r/NicotinePouch/comments/1anot67/sesh_doesnt_get_much_mention_around_here/krmlz7r/",
                    "subreddit_type": "public",
                    "link_permalink": "https://www.reddit.com/r/NicotinePouch/comments/1anot67/sesh_doesnt_get_much_mention_around_here/",
                    "name": "t1_krmlz7r",
                    "author_flair_template_id": null,
                    "subreddit_name_prefixed": "r/NicotinePouch",
                    "author_flair_text": null,
                    "treatment_tags": [],
                    "created": 1708619803.0,
                    "created_utc": 1708619803.0,
                    "awarders": [],
                    "all_awardings": [],
                    "locked": false,
                    "author_flair_background_color": null,
                    "collapsed_because_crowd_control": null,
                    "mod_reports": [],
                    "quarantine": false,
                    "mod_note": null,
                    "link_url": "https://i.redd.it/3zxcetvecthc1.jpeg"
                }
            }
        ],
        "before": null
    }
}